aion_optimizer/__init__.py
aion_optimizer/config.py
aion_optimizer/data_cleaner.py
aion_optimizer/data_preprocessor.py
aion_optimizer/hyperparam_config.json
aion_optimizer/optimizer.py
aion_optimizer/test.py
aion_optimizer-0.1.1.dist-info/LICENCE
aion_optimizer-0.1.1.dist-info/METADATA
aion_optimizer-0.1.1.dist-info/WHEEL
aion_optimizer-0.1.1.dist-info/top_level.txt
aion_optimizer-0.1.1.dist-info/RECORD
