Metadata-Version: 2.1
Name: aion_optimizer
Version: 0.1.1
Summary: An automated machine learning optimization package
Home-page: https://github.com/
Author: Lalit Lohani
Author-email: lohanilalit.01@gmail.com
Classifier: Programming Language :: Python :: 3
Classifier: License :: OSI Approved :: MIT License
Classifier: Operating System :: OS Independent
Requires-Python: >=3.8
License-File: LICENCE
Requires-Dist: numpy >=1.19.0
Requires-Dist: pandas >=1.2.0
Requires-Dist: scikit-learn >=0.24.0
Requires-Dist: scipy
Requires-Dist: xgboost
Requires-Dist: catboost
